buildpan/__init__.py
buildpan/access_token.py
buildpan/buildpan.py
buildpan/create_file.py
buildpan/deployer.py
buildpan/find_path.py
buildpan/installer.py
buildpan/platform_installer.py
buildpan/previous_commit.py
buildpan/read_file.py
buildpan/repo_pull.py
buildpan/setting.py
buildpan/workflow.py
buildpan/yaml_reader.py
ci_commands/__init__.py
ci_commands/bitbucket_webhook.py
ci_commands/encrypt.py
ci_commands/github_webhook.py
ci_commands/init.py
ci_commands/pull.py
ci_commands/start.py
ci_commands/stop.py
ci_commands/stop_all.py
ci_commands/version.py
cicdcli-1.7.dist-info/METADATA
cicdcli-1.7.dist-info/WHEEL
cicdcli-1.7.dist-info/entry_points.txt
cicdcli-1.7.dist-info/top_level.txt
cicdcli-1.7.dist-info/RECORD
